{"dataset_name": "CIFAR10", "batch_size": "128", "max_epoch": "300", "data_dir": "dataset/data/CIFAR10", "train_data": "Dataset CIFAR10\n    Number of datapoints: 50000\n    Root location: dataset/data/CIFAR10\n    Split: Train\n    StandardTransform\nTransform: ToTensor()", "test_data": "Dataset CIFAR10\n    Number of datapoints: 10000\n    Root location: dataset/data/CIFAR10\n    Split: Test\n    StandardTransform\nTransform: ToTensor()", "kw_loader": "{'num_workers': 0}", "model_name": "DenseNetBC24", "kw_model": "{}", "kw_optimizer": "{}", "scheduler": "None", "kw_scheduler": "{'lr_lambda': <function cifar10.<locals>.<lambda> at 0x7f44d9738cc0>}", "device": "cuda:0", "result_dir": "./result/CIFAR10/DenseNetBC24"}